lexer/__init__.py
lexer/finesse.py
pygments_finesse-0.1.dist-info/LICENSE
pygments_finesse-0.1.dist-info/METADATA
pygments_finesse-0.1.dist-info/WHEEL
pygments_finesse-0.1.dist-info/entry_points.txt
pygments_finesse-0.1.dist-info/top_level.txt
pygments_finesse-0.1.dist-info/RECORD
