Metadata-Version: 2.1
Name: pygments-finesse
Version: 0.1
Summary: Pygments lexer for finesse kat files.
Home-page: https://github.com/philj56/pygments-finesse
Author: Philip Jones
Author-email: UNKNOWN
License: UNKNOWN
Keywords: pygments syntax highlighting
Platform: UNKNOWN
Classifier: Programming Language :: Python :: 3
Classifier: License :: OSI Approved :: MIT License
Classifier: Operating System :: OS Independent
Requires-Dist: pygments (>=2)
